{
  "Version": "2012-10-17",
  "Statement": [
    {
      "Sid": "SSMCoreAccess",
      "Effect": "Allow",
      "Action": [
        "ssm:UpdateInstanceInformation",
        "ssmmessages:CreateControlChannel",
        "ssmmessages:CreateDataChannel",
        "ssmmessages:OpenControlChannel",
        "ssmmessages:OpenDataChannel"
      ],
      "Resource": "*"
    },
    {
      "Sid": "EC2MetadataReadOnly",
      "Effect": "Allow",
      "Action": "ec2:DescribeInstanceStatus",
      "Resource": "*"
    }
  ]
}
